[{"name":"sql.active_record","payload":{"sql":"SELECT  \"menus\".* FROM \"menus\" WHERE \"menus\".\"descriptor\" = $1 LIMIT $2","name":"Menu Load","connection_id":69998303367960,"statement_name":null,"binds":[{"name":"descriptor","value_before_type_cast":"main_menu","type":{"precision":null,"scale":null,"limit":null},"original_attribute":null,"value":"main_menu","value_for_database":"main_menu"},{"name":"LIMIT","value_before_type_cast":1,"type":{"precision":null,"scale":null,"limit":null},"original_attribute":null,"value":1}],"line":8,"filename":"/home/dima/Rails/laston_cms/app/controllers/site_controller.rb","method":"all_pages_data"},"time":"2017-04-26T12:29:43.348+03:00","transaction_id":"f1d6e9000852603f9a2f","end":"2017-04-26T12:29:43.349+03:00","children":[],"duration":1.094744},{"name":"sql.active_record","payload":{"sql":"SELECT  \"menus\".* FROM \"menus\" WHERE \"menus\".\"descriptor\" = $1 LIMIT $2","name":"Menu Load","connection_id":69998303367960,"statement_name":null,"binds":[{"name":"descriptor","value_before_type_cast":"footer_menu","type":{"precision":null,"scale":null,"limit":null},"original_attribute":null,"value":"footer_menu","value_for_database":"footer_menu"},{"name":"LIMIT","value_before_type_cast":1,"type":{"precision":null,"scale":null,"limit":null},"original_attribute":null,"value":1}],"line":10,"filename":"/home/dima/Rails/laston_cms/app/controllers/site_controller.rb","method":"all_pages_data"},"time":"2017-04-26T12:29:43.351+03:00","transaction_id":"f1d6e9000852603f9a2f","end":"2017-04-26T12:29:43.354+03:00","children":[],"duration":3.291718},{"name":"sql.active_record","payload":{"sql":"SELECT  \"pages\".* FROM \"pages\" WHERE \"pages\".\"descriptor\" = $1 LIMIT $2","name":"Page Load","connection_id":69998303367960,"statement_name":null,"binds":[{"name":"descriptor","value_before_type_cast":"home","type":{"precision":null,"scale":null,"limit":null},"original_attribute":null,"value":"home","value_for_database":"home"},{"name":"LIMIT","value_before_type_cast":1,"type":{"precision":null,"scale":null,"limit":null},"original_attribute":null,"value":1}],"line":4,"filename":"/home/dima/Rails/laston_cms/app/controllers/site/static_pages_controller.rb","method":"home"},"time":"2017-04-26T12:29:43.356+03:00","transaction_id":"f1d6e9000852603f9a2f","end":"2017-04-26T12:29:43.358+03:00","children":[],"duration":1.8303239999999998},{"name":"sql.active_record","payload":{"sql":"SELECT  \"sliders\".* FROM \"sliders\" WHERE \"sliders\".\"descriptor\" = $1 LIMIT $2","name":"Slider Load","connection_id":69998303367960,"statement_name":null,"binds":[{"name":"descriptor","value_before_type_cast":"main","type":{"precision":null,"scale":null,"limit":null},"original_attribute":null,"value":"main","value_for_database":"main"},{"name":"LIMIT","value_before_type_cast":1,"type":{"precision":null,"scale":null,"limit":null},"original_attribute":null,"value":1}],"line":5,"filename":"/home/dima/Rails/laston_cms/app/controllers/site/static_pages_controller.rb","method":"home"},"time":"2017-04-26T12:29:43.359+03:00","transaction_id":"f1d6e9000852603f9a2f","end":"2017-04-26T12:29:43.360+03:00","children":[],"duration":1.340048},{"name":"sql.active_record","payload":{"sql":"SELECT  \"products\".* FROM \"products\" ORDER BY \"products\".\"id\" DESC LIMIT $1","name":"Product Load","connection_id":69998303367960,"statement_name":null,"binds":[{"name":"LIMIT","value_before_type_cast":5,"type":{"precision":null,"scale":null,"limit":null},"original_attribute":null,"value":5}],"line":6,"filename":"/home/dima/Rails/laston_cms/app/controllers/site/static_pages_controller.rb","method":"home"},"time":"2017-04-26T12:29:43.362+03:00","transaction_id":"f1d6e9000852603f9a2f","end":"2017-04-26T12:29:43.363+03:00","children":[],"duration":1.1574440000000001},{"name":"sql.active_record","payload":{"sql":"SELECT \"slides\".* FROM \"slides\" WHERE \"slides\".\"slider_id\" = $1","name":"Slide Load","connection_id":69998303367960,"statement_name":null,"binds":[{"name":"slider_id","value_before_type_cast":10,"type":{"precision":null,"scale":null,"limit":null,"range":"-2147483648...2147483648"},"original_attribute":null,"value":10,"value_for_database":10}],"line":11,"filename":"/home/dima/Rails/laston_cms/app/views/site/static_pages/home.html.erb","method":"_app_views_site_static_pages_home_html_erb__3182981618940939934_47383063622980"},"time":"2017-04-26T12:29:43.373+03:00","transaction_id":"f1d6e9000852603f9a2f","end":"2017-04-26T12:29:43.374+03:00","children":[],"duration":1.341227},{"name":"sql.active_record","payload":{"sql":"SELECT  \"products\".* FROM \"products\" ORDER BY \"products\".\"price\" ASC LIMIT $1","name":"Product Load","connection_id":69998303367960,"statement_name":null,"binds":[{"name":"LIMIT","value_before_type_cast":5,"type":{"precision":null,"scale":null,"limit":null},"original_attribute":null,"value":5}],"line":62,"filename":"/home/dima/Rails/laston_cms/app/views/site/static_pages/home.html.erb","method":"_app_views_site_static_pages_home_html_erb__3182981618940939934_47383063622980"},"time":"2017-04-26T12:29:43.384+03:00","transaction_id":"f1d6e9000852603f9a2f","end":"2017-04-26T12:29:43.385+03:00","children":[],"duration":1.45115},{"name":"render_template.action_view","payload":{"identifier":"/home/dima/Rails/laston_cms/app/views/site/static_pages/home.html.erb","layout":"layouts/site"},"time":"2017-04-26T12:29:43.368+03:00","transaction_id":"f6fe7942bcdf0da78408","end":"2017-04-26T12:29:43.394+03:00","children":[],"duration":25.948572},{"name":"sql.active_record","payload":{"sql":"SELECT \"menu_items\".* FROM \"menu_items\" WHERE \"menu_items\".\"menu_id\" = $1 AND \"menu_items\".\"ancestry\" IS NULL","name":"MenuItem Load","connection_id":69998303367960,"statement_name":null,"binds":[{"name":"menu_id","value_before_type_cast":3,"type":{"precision":null,"scale":null,"limit":null,"range":"-2147483648...2147483648"},"original_attribute":null,"value":3,"value_for_database":3}],"line":83,"filename":"/home/dima/Rails/laston_cms/app/views/layouts/site/_header.html.erb","method":"_app_views_layouts_site__header_html_erb___3135994849306474040_69998176746960"},"time":"2017-04-26T12:29:43.414+03:00","transaction_id":"f1d6e9000852603f9a2f","end":"2017-04-26T12:29:43.416+03:00","children":[],"duration":1.4430619999999998},{"name":"sql.active_record","payload":{"sql":"SELECT  1 AS one FROM \"menu_items\" WHERE \"menu_items\".\"ancestry\" = '66' LIMIT $1","name":"MenuItem Exists","connection_id":69998303367960,"statement_name":null,"binds":[{"name":"LIMIT","value_before_type_cast":1,"type":{"precision":null,"scale":null,"limit":null},"original_attribute":null,"value":1}],"line":84,"filename":"/home/dima/Rails/laston_cms/app/views/layouts/site/_header.html.erb","method":"block in _app_views_layouts_site__header_html_erb___3135994849306474040_69998176746960"},"time":"2017-04-26T12:29:43.418+03:00","transaction_id":"f1d6e9000852603f9a2f","end":"2017-04-26T12:29:43.419+03:00","children":[],"duration":1.161095},{"name":"sql.active_record","payload":{"sql":"SELECT \"menu_items\".* FROM \"menu_items\" WHERE \"menu_items\".\"ancestry\" = '66'","name":"MenuItem Load","connection_id":69998303367960,"statement_name":null,"binds":[],"line":92,"filename":"/home/dima/Rails/laston_cms/app/views/layouts/site/_header.html.erb","method":"block in _app_views_layouts_site__header_html_erb___3135994849306474040_69998176746960"},"time":"2017-04-26T12:29:43.421+03:00","transaction_id":"f1d6e9000852603f9a2f","end":"2017-04-26T12:29:43.423+03:00","children":[],"duration":2.485518},{"name":"sql.active_record","payload":{"sql":"SELECT  1 AS one FROM \"menu_items\" WHERE \"menu_items\".\"ancestry\" = '67' LIMIT $1","name":"MenuItem Exists","connection_id":69998303367960,"statement_name":null,"binds":[{"name":"LIMIT","value_before_type_cast":1,"type":{"precision":null,"scale":null,"limit":null},"original_attribute":null,"value":1}],"line":84,"filename":"/home/dima/Rails/laston_cms/app/views/layouts/site/_header.html.erb","method":"block in _app_views_layouts_site__header_html_erb___3135994849306474040_69998176746960"},"time":"2017-04-26T12:29:43.426+03:00","transaction_id":"f1d6e9000852603f9a2f","end":"2017-04-26T12:29:43.427+03:00","children":[],"duration":1.083358},{"name":"sql.active_record","payload":{"sql":"SELECT \"menu_items\".* FROM \"menu_items\" WHERE \"menu_items\".\"ancestry\" = '67'","name":"MenuItem Load","connection_id":69998303367960,"statement_name":null,"binds":[],"line":92,"filename":"/home/dima/Rails/laston_cms/app/views/layouts/site/_header.html.erb","method":"block in _app_views_layouts_site__header_html_erb___3135994849306474040_69998176746960"},"time":"2017-04-26T12:29:43.429+03:00","transaction_id":"f1d6e9000852603f9a2f","end":"2017-04-26T12:29:43.430+03:00","children":[],"duration":1.069752},{"name":"sql.active_record","payload":{"sql":"SELECT  1 AS one FROM \"menu_items\" WHERE \"menu_items\".\"ancestry\" = '68' LIMIT $1","name":"MenuItem Exists","connection_id":69998303367960,"statement_name":null,"binds":[{"name":"LIMIT","value_before_type_cast":1,"type":{"precision":null,"scale":null,"limit":null},"original_attribute":null,"value":1}],"line":84,"filename":"/home/dima/Rails/laston_cms/app/views/layouts/site/_header.html.erb","method":"block in _app_views_layouts_site__header_html_erb___3135994849306474040_69998176746960"},"time":"2017-04-26T12:29:43.432+03:00","transaction_id":"f1d6e9000852603f9a2f","end":"2017-04-26T12:29:43.433+03:00","children":[],"duration":1.032844},{"name":"sql.active_record","payload":{"sql":"SELECT \"menu_items\".* FROM \"menu_items\" WHERE \"menu_items\".\"ancestry\" = '68'","name":"MenuItem Load","connection_id":69998303367960,"statement_name":null,"binds":[],"line":92,"filename":"/home/dima/Rails/laston_cms/app/views/layouts/site/_header.html.erb","method":"block in _app_views_layouts_site__header_html_erb___3135994849306474040_69998176746960"},"time":"2017-04-26T12:29:43.435+03:00","transaction_id":"f1d6e9000852603f9a2f","end":"2017-04-26T12:29:43.436+03:00","children":[],"duration":1.203528},{"name":"render_partial.action_view","payload":{"identifier":"/home/dima/Rails/laston_cms/app/views/layouts/site/_header.html.erb"},"time":"2017-04-26T12:29:43.412+03:00","transaction_id":"f6fe7942bcdf0da78408","end":"2017-04-26T12:29:43.438+03:00","children":[],"duration":25.507304},{"name":"sql.active_record","payload":{"sql":"SELECT \"menu_items\".* FROM \"menu_items\" WHERE \"menu_items\".\"menu_id\" = $1","name":"MenuItem Load","connection_id":69998303367960,"statement_name":null,"binds":[{"name":"menu_id","value_before_type_cast":4,"type":{"precision":null,"scale":null,"limit":null,"range":"-2147483648...2147483648"},"original_attribute":null,"value":4,"value_for_database":4}],"line":6,"filename":"/home/dima/Rails/laston_cms/app/views/layouts/site/_footer.html.erb","method":"_app_views_layouts_site__footer_html_erb__4034284775094817087_69998176456940"},"time":"2017-04-26T12:29:43.443+03:00","transaction_id":"f1d6e9000852603f9a2f","end":"2017-04-26T12:29:43.444+03:00","children":[],"duration":1.326582},{"name":"render_partial.action_view","payload":{"identifier":"/home/dima/Rails/laston_cms/app/views/layouts/site/_footer.html.erb"},"time":"2017-04-26T12:29:43.440+03:00","transaction_id":"f6fe7942bcdf0da78408","end":"2017-04-26T12:29:43.446+03:00","children":[],"duration":5.812539999999999},{"name":"process_action.action_controller","payload":{"controller":"Site::StaticPagesController","action":"home","params":{"controller":"site/static_pages","action":"home"},"headers":"Not JSON Encodable","format":"html","method":"GET","path":"/","status":200,"view_runtime":80.6405040002637,"db_runtime":14.319085},"time":"2017-04-26T12:29:43.348+03:00","transaction_id":"f6fe7942bcdf0da78408","end":"2017-04-26T12:29:43.455+03:00","children":[],"duration":107.504447}]